consolemenu-stubs/METADATA.toml
consolemenu-stubs/__init__.pyi
consolemenu-stubs/console_menu.pyi
consolemenu-stubs/menu_component.pyi
consolemenu-stubs/menu_formatter.pyi
consolemenu-stubs/multiselect_menu.pyi
consolemenu-stubs/prompt_utils.pyi
consolemenu-stubs/py.typed
consolemenu-stubs/screen.pyi
consolemenu-stubs/selection_menu.pyi
consolemenu-stubs/version.pyi
consolemenu-stubs/format/__init__.pyi
consolemenu-stubs/format/menu_borders.pyi
consolemenu-stubs/format/menu_margins.pyi
consolemenu-stubs/format/menu_padding.pyi
consolemenu-stubs/format/menu_style.pyi
consolemenu-stubs/items/__init__.pyi
consolemenu-stubs/items/command_item.pyi
consolemenu-stubs/items/external_item.pyi
consolemenu-stubs/items/function_item.pyi
consolemenu-stubs/items/selection_item.pyi
consolemenu-stubs/items/submenu_item.pyi
consolemenu-stubs/validators/__init__.pyi
consolemenu-stubs/validators/base.pyi
consolemenu-stubs/validators/regex.pyi
consolemenu-stubs/validators/url.pyi
types_console_menu-0.8.0.20250326.dist-info/licenses/LICENSE
types_console_menu-0.8.0.20250326.dist-info/METADATA
types_console_menu-0.8.0.20250326.dist-info/WHEEL
types_console_menu-0.8.0.20250326.dist-info/top_level.txt
types_console_menu-0.8.0.20250326.dist-info/RECORD
